Workbook
Name AsOfDate: 'Read me'!$B$7

Sheet Read me
A1: ZAV-HZN Cutover Plan v0.3
A2: Fictitious test data – Copilot for Frontier Consultancy scenario testing
A4: Purpose | B4: Draft cutover runbook (v0.3) for the Zava Horizon go-live: D365 Finance + Supply Chain (F&O) and D365 Sales / Customer Service (CE). Cutover weekend Fri 26 Feb – Sun 28 Feb 2027, go-live Mon 1 Mar 2027. Use for testing runbook review, dependency checking, critical path, Go/No-Go preparation and owner briefings.
A5: Programme | B5: Zava Horizon (ZAV-HZN) – Zava LLC, delivered by Frontier Consulting
A6: Data as of | B6: Monday 19 Oct 2026 (Dubai, UTC+4)
A7: As-of date (used in formulas) | B7: 46314
A8: Currency | B8: AED
A9: Prepared by | B9: Priya Nair, Project Manager (Frontier Consulting) – scenario owner Lorette Roos
A11: Sheet | B11: Contents
A12: Runbook | B12: 112 tasks across Pre-cutover (T-14 to T-1), Freeze, Data migration, Technical, Business validation, three Go/No-Go gates, Go-live and Hypercare day 1. Planned end = planned start + duration.
A13: Phase summary | B13: Task counts, earliest start, latest finish and total hours by phase (formulas).
A15: Version | B15: v0.3 DRAFT – for review at design authority; not yet baselined. Times are Gulf Standard Time (UTC+4).
A16: Go/No-Go gates | B16: Gate 1 Fri 26 Feb (start data migration) | Gate 2 Sat 27 Feb (start business validation) | Gate 3 Sun 28 Feb 16:00 (final Go/No-Go)
A18: Important | B18: Fictitious test data – Copilot for Frontier Consultancy scenario testing. All companies, people and figures are fictitious and must not be used for real decisions.

Sheet Runbook
A1: ZAV-HZN Cutover Plan v0.3 (DRAFT) | Fictitious test data – Copilot for Frontier Consultancy scenario testing
A2: Task ID | B2: Phase | C2: Task | D2: Planned start | E2: Planned end | F2: Duration (h) | G2: Predecessor IDs | H2: Owner | I2: Team | J2: Status | K2: Evidence required | L2: Comments
A3: CUT-001 | B3: Pre-cutover (T-14 to T-1) | C3: Cutover plan v1.0 baselined and circulated | D3: 46430.375 | E3: =D3+F3/24 -> 46430.542 | F3: 4 | H3: Priya Nair | I3: PMO | J3: In planning | K3: Signed cutover plan | L3: T-14
A4: CUT-002 | B4: Pre-cutover (T-14 to T-1) | C4: Confirm cutover roles, rota and contact list | D4: 46430.542 | E4: =D4+F4/24 -> 46430.708 | F4: 4 | G4: CUT-001 | H4: Priya Nair | I4: PMO | J4: In planning | K4: Contact list in Teams channel
A5: CUT-003 | B5: Pre-cutover (T-14 to T-1) | C5: Production environment deployed with final release package | D5: 46430.417 | E5: =D5+F5/24 -> 46430.75 | F5: 8 | H5: Arjun Mehta | I5: Frontier – Integration | J5: In planning | K5: LCS/PPAC deployment log
A6: CUT-004 | B6: Pre-cutover (T-14 to T-1) | C6: CE production solutions imported (managed) | D6: 46430.75 | E6: =D6+F6/24 -> 46430.917 | F6: 4 | G6: CUT-003 | H6: Arjun Mehta | I6: Frontier – CE | J6: In planning | K6: Solution import history
A7: CUT-005 | B7: Pre-cutover (T-14 to T-1) | C7: Security roles and user access provisioned in F&O and CE | D7: 46433.375 | E7: =D7+F7/24 -> 46434.042 | F7: 16 | G7: CUT-003 | H7: Ravi Kumar | I7: Zava IT | J7: Not started | K7: User access report
A8: CUT-006 | B8: Pre-cutover (T-14 to T-1) | C8: Final mock cutover (Mock 3) results signed off | D8: 46433.375 | E8: =D8+F8/24 -> 46433.708 | F8: 8 | H8: Noura Al Hashimi | I8: Frontier – Data | J8: Not started | K8: Mock 3 reconciliation pack | L8: Mock 3 ran 6–7 Feb
A9: CUT-007 | B9: Pre-cutover (T-14 to T-1) | C9: Static master data loaded to production (COA, dimensions, posting profiles) | D9: 46433.542 | E9: =D9+F9/24 -> 46434.042 | F9: 12 | G9: CUT-003, CUT-006 | H9: Noura Al Hashimi | I9: Frontier – Data | J9: Not started | K9: Load log and record counts
A10: CUT-008 | B10: Pre-cutover (T-14 to T-1) | C10: Vendor master (de-duplicated) loaded to production | D10: 46434.042 | E10: =D10+F10/24 -> 46434.375 | F10: 8 | G10: CUT-007 | H10: Noura Al Hashimi | I10: Frontier – Data | J10: Not started | K10: Dedup report and load log
A11: CUT-009 | B11: Pre-cutover (T-14 to T-1) | C11: Customer master loaded to production | D11: 46434.375 | E11: =D11+F11/24 -> 46434.708 | F11: 8 | G11: CUT-008 | H11: Noura Al Hashimi | I11: Frontier – Data | J11: Not started | K11: Load log
A12: CUT-010 | B12: Pre-cutover (T-14 to T-1) | C12: Vendor and customer master sign-off by Group Financial Controller | D12: 46434.708 | E12: =D12+F12/24 -> 46434.875 | F12: 4 | G12: CUT-009 | H12: Hassan Ali | I12: Zava Finance | J12: Not started | K12: Signed master data sign-off
A13: CUT-011 | B13: Pre-cutover (T-14 to T-1) | C13: Fixed asset register loaded and reconciled | D13: 46434.875 | E13: =D13+F13/24 -> 46435.208 | F13: 8 | G13: CUT-010 | H13: James Okafor | I13: Frontier – Finance | J13: Not started | K13: FA reconciliation
A14: CUT-012 | B14: Pre-cutover (T-14 to T-1) | C14: Warehouse locations, zones and license plates set up | D14: 46434.375 | E14: =D14+F14/24 -> 46434.875 | F14: 12 | G14: CUT-007 | H14: Rahul Verma | I14: Frontier – Supply Chain | J14: Not started | K14: Location count report
A15: CUT-013 | B15: Pre-cutover (T-14 to T-1) | C15: Warehouse mobile devices configured and tested on production | D15: 46435.375 | E15: =D15+F15/24 -> 46435.708 | F15: 8 | G15: CUT-012 | H15: Grace Lee | I15: Zava Warehouse | J15: Not started | K15: Device test checklist
A16: CUT-014 | B16: Pre-cutover (T-14 to T-1) | C16: Trade agreements and freight rate cards loaded | D16: 46434.375 | E16: =D16+F16/24 -> 46434.708 | F16: 8 | G16: CUT-007 | H16: Lina Mansour | I16: Frontier – CE | J16: Not started | K16: Rate card comparison
A17: CUT-015 | B17: Pre-cutover (T-14 to T-1) | C17: CargoWise production connection tested (read-only) | D17: 46435.375 | E17: =D17+F17/24 -> 46435.625 | F17: 6 | G17: CUT-003 | H17: Arjun Mehta | I17: Frontier – Integration | J17: Not started | K17: Connection test log
A18: CUT-016 | B18: Pre-cutover (T-14 to T-1) | C18: ZATCA e-invoicing ISV production onboarding for ZVSA | D18: 46435.625 | E18: =D18+F18/24 -> 46435.958 | F18: 8 | G18: CUT-015 | H18: James Okafor | I18: Frontier – Finance | J18: Not started | K18: ZATCA onboarding certificate (CSID)
A19: CUT-017 | B19: Pre-cutover (T-14 to T-1) | C19: Bank integration production certificates installed (UAE, KSA, Oman) | D19: 46435.958 | E19: =D19+F19/24 -> 46436.208 | F19: 6 | G19: CUT-016 | H19: Ravi Kumar | I19: Zava IT | J19: Not started | K19: Certificate install log
A20: CUT-018 | B20: Pre-cutover (T-14 to T-1) | C20: Batch jobs created (disabled) and schedule documented | D20: 46436.375 | E20: =D20+F20/24 -> 46436.625 | F20: 6 | G20: CUT-003 | H20: Arjun Mehta | I20: Frontier – Integration | J20: Not started | K20: Batch job list
A21: CUT-019 | B21: Pre-cutover (T-14 to T-1) | C21: Printer and label configuration for warehouse documents | D21: 46436.625 | E21: =D21+F21/24 -> 46436.792 | F21: 4 | G21: CUT-018 | H21: Ravi Kumar | I21: Zava IT | J21: Not started | K21: Test print evidence
A22: CUT-020 | B22: Pre-cutover (T-14 to T-1) | C22: End-user training completion confirmed (>= 90%) | D22: 46436.375 | E22: =D22+F22/24 -> 46436.542 | F22: 4 | H22: Tom Becker | I22: Frontier – Change | J22: Not started | K22: Training completion report
A23: CUT-021 | B23: Pre-cutover (T-14 to T-1) | C23: Go-live communications issued to staff and customers | D23: 46436.542 | E23: =D23+F23/24 -> 46436.625 | F23: 2 | G23: CUT-020 | H23: Elena Petrova | I23: Zava HR & Change | J23: Not started | K23: Comms email and intranet post
A24: CUT-022 | B24: Pre-cutover (T-14 to T-1) | C24: Legacy GP 2018 and Tally period-end close completed (Jan 2027) | D24: 46437.375 | E24: =D24+F24/24 -> 46438.042 | F24: 16 | H24: Hassan Ali | I24: Zava Finance | J24: Not started | K24: Close checklist
A25: CUT-023 | B25: Pre-cutover (T-14 to T-1) | C25: Hypercare support model and ticket queues ready | D25: 46440.375 | E25: =D25+F25/24 -> 46440.542 | F25: 4 | H25: Priya Nair | I25: PMO | J25: Not started | K25: Hypercare runbook
A26: CUT-024 | B26: Pre-cutover (T-14 to T-1) | C26: Cutover rehearsal walkthrough (table-top) | D26: 46441.417 | E26: =D26+F26/24 -> 46441.542 | F26: 3 | G26: CUT-002 | H26: Priya Nair | I26: PMO | J26: Not started | K26: Attendance and actions
A27: CUT-025 | B27: Pre-cutover (T-14 to T-1) | C27: Open items extract scripts validated against Mock 3 | D27: 46441.583 | E27: =D27+F27/24 -> 46441.75 | F27: 4 | G27: CUT-006 | H27: Noura Al Hashimi | I27: Frontier – Data | J27: Not started | K27: Script sign-off
A28: CUT-026 | B28: Pre-cutover (T-14 to T-1) | C28: Customer and vendor notification of new bank details/invoice format | D28: 46441.75 | E28: =D28+F28/24 -> 46441.917 | F28: 4 | G28: CUT-025 | H28: Samir Haddad | I28: Zava Customer Service | J28: Not started | K28: Notification log
A29: CUT-027 | B29: Pre-cutover (T-14 to T-1) | C29: Readiness checkpoint with sponsor (T-2) | D29: 46442.458 | E29: =D29+F29/24 -> 46442.5 | F29: 1 | G29: CUT-024, CUT-025 | H29: Nadia Farouk | I29: Zava Sponsor | J29: Not started | K29: Readiness checklist | L29: T-2
A30: CUT-028 | B30: Pre-cutover (T-14 to T-1) | C30: Final backup of legacy systems scheduled | D30: 46443.375 | E30: =D30+F30/24 -> 46443.458 | F30: 2 | H30: Ravi Kumar | I30: Zava IT | J30: Not started | K30: Backup schedule
A31: CUT-029 | B31: Freeze | C31: Freeze new sales quotes and orders in Salesforce / legacy | D31: 46444.5 | E31: =D31+F31/24 -> 46444.542 | F31: 1 | G31: CUT-027 | H31: Lina Mansour | I31: Frontier – CE | J31: Not started | K31: Freeze confirmation email
A32: CUT-030 | B32: Freeze | C32: Freeze AP invoice entry in GP 2018 and Tally | D32: 46444.5 | E32: =D32+F32/24 -> 46444.542 | F32: 1 | G32: CUT-027 | H32: Hassan Ali | I32: Zava Finance | J32: Not started | K32: Freeze confirmation
A33: CUT-031 | B33: Freeze | C33: Freeze AR invoicing and cash receipts in legacy | D33: 46444.5 | E33: =D33+F33/24 -> 46444.542 | F33: 1 | G33: CUT-027 | H33: Hassan Ali | I33: Zava Finance | J33: Not started | K33: Freeze confirmation
A34: CUT-032 | B34: Freeze | C34: Freeze warehouse transactions in legacy WMS (stock count start) | D34: 46444.542 | E34: =D34+F34/24 -> 46444.583 | F34: 1 | G34: CUT-027 | H34: Grace Lee | I34: Zava Warehouse | J34: Not started | K34: Freeze confirmation
A35: CUT-033 | B35: Freeze | C35: CargoWise outbound messages paused | D35: 46444.542 | E35: =D35+F35/24 -> 46444.583 | F35: 1 | G35: CUT-027 | H35: Arjun Mehta | I35: Frontier – Integration | J35: Not started | K35: Queue screenshot
A36: CUT-034 | B36: Freeze | C36: Physical stock count at Jebel Ali DC | D36: 46444.583 | E36: =D36+F36/24 -> 46444.75 | F36: 4 | G36: CUT-033 | H36: Grace Lee | I36: Zava Warehouse | J36: Not started | K36: Signed count sheets
A37: CUT-035 | B37: Freeze | C37: Legacy systems set to read-only | D37: 46444.583 | E37: =D37+F37/24 -> 46444.625 | F37: 1 | G37: CUT-029, CUT-030, CUT-031 | H37: Ravi Kumar | I37: Zava IT | J37: Not started | K37: Access change record
A38: CUT-036 | B38: Freeze | C38: Final legacy backups taken | D38: 46444.625 | E38: =D38+F38/24 -> 46444.708 | F38: 2 | G38: CUT-035 | H38: Ravi Kumar | I38: Zava IT | J38: Not started | K38: Backup log
A39: CUT-037 | B39: Freeze | C39: Closing trial balances extracted per entity (ZVAE, ZVSA, ZVOM, ZVQA, ZVHQ) | D39: 46444.708 | E39: =D39+F39/24 -> 46444.792 | F39: 2 | G39: CUT-036 | H39: James Okafor | I39: Frontier – Finance | J39: Not started | K39: Trial balance extracts
A40: CUT-038 | B40: Freeze | C40: Freeze confirmation to cutover lead | D40: 46444.792 | E40: =D40+F40/24 -> 46444.813 | F40: 0.5 | G40: CUT-034, CUT-037 | H40: Priya Nair | I40: PMO | J40: Not started | K40: Teams post in cutover channel
A41: CUT-039 | B41: Go/No-Go gates | C41: Gate 1 pre-read: freeze, backups and trial balances complete | D41: 46444.812 | E41: =D41+F41/24 -> 46444.833 | F41: 0.5 | G41: CUT-038 | H41: Priya Nair | I41: PMO | J41: Not started | K41: Gate 1 checklist
A42: CUT-040 | B42: Go/No-Go gates | C42: Gate 1 – Go/No-Go to start data migration | D42: 46444.833 | E42: =D42+F42/24 -> 46444.854 | F42: 0.5 | G42: CUT-039 | H42: Nadia Farouk | I42: Zava Sponsor | J42: Not started | K42: Gate 1 decision recorded | L42: Go/No-Go gate 1
A43: CUT-041 | B43: Data migration | C43: Open AR items extracted from legacy | D43: 46444.854 | E43: =D43+F43/24 -> 46444.917 | F43: 1.5 | G43: CUT-040 | H43: Noura Al Hashimi | I43: Frontier – Data | J43: Not started | K43: Extract log
A44: CUT-042 | B44: Data migration | C44: Open AR items transformed and validated | D44: 46444.917 | E44: =D44+F44/24 -> 46444.979 | F44: 1.5 | G44: CUT-041 | H44: Noura Al Hashimi | I44: Frontier – Data | J44: Not started | K44: Validation report
A45: CUT-043 | B45: Data migration | C45: Open AR items loaded to D365 Finance | D45: 46444.979 | E45: =D45+F45/24 -> 46445.063 | F45: 2 | G45: CUT-042 | H45: Noura Al Hashimi | I45: Frontier – Data | J45: Not started | K45: Load log
A46: CUT-044 | B46: Data migration | C46: Open AP items extracted from legacy | D46: 46444.854 | E46: =D46+F46/24 -> 46444.917 | F46: 1.5 | G46: CUT-040 | H46: Noura Al Hashimi | I46: Frontier – Data | J46: Not started | K46: Extract log
A47: CUT-045 | B47: Data migration | C47: Open AP items transformed and validated | D47: 46444.917 | E47: =D47+F47/24 -> 46444.979 | F47: 1.5 | G47: CUT-044 | H47: Noura Al Hashimi | I47: Frontier – Data | J47: Not started | K47: Validation report
A48: CUT-046 | B48: Data migration | C48: Load open AP invoices to D365 Finance | D48: 46444.979 | E48: =D48+F48/24 -> 46445.063 | F48: 2 | G48: CUT-045, CUT-048 | H48: Noura Al Hashimi | I48: Frontier – Data | J48: Not started | K48: Load log
A49: CUT-047 | B49: Data migration | C49: Validate AP load counts and amounts | D49: 46445.062 | E49: =D49+F49/24 -> 46445.104 | F49: 1 | G49: CUT-046 | H49: Hassan Ali | I49: Zava Finance | J49: Not started | K49: Count reconciliation
A50: CUT-048 | B50: Data migration | C50: Reconcile AP sub-ledger to GL | D50: 46445.104 | E50: =D50+F50/24 -> 46445.146 | F50: 1 | G50: CUT-047 | H50: James Okafor | I50: Frontier – Finance | J50: Not started | K50: AP reconciliation
A51: CUT-049 | B51: Data migration | C51: Opening GL balances loaded per entity | D51: 46445.062 | E51: =D51+F51/24 -> 46445.146 | F51: 2 | G51: CUT-043 | H51: James Okafor | I51: Frontier – Finance | J51: Not started | K51: Journal posting log
A52: CUT-050 | B52: Data migration | C52: Trial balance reconciliation legacy vs D365 (all entities) | D52: 46445.146 | E52: =D52+F52/24 -> 46445.229 | F52: 2 | G52: CUT-049, CUT-048 | H52: Hassan Ali | I52: Zava Finance | J52: Not started | K52: Signed TB reconciliation
A53: CUT-051 | B53: Data migration | C53: Bank balances loaded and reconciled | D53: 46445.229 | E53: =D53+F53/24 -> 46445.271 | F53: 1 | G53: CUT-050 | H53: James Okafor | I53: Frontier – Finance | J53: Not started | K53: Bank reconciliation
A54: CUT-052 | B54: Data migration | C54: Fixed asset NBV reconciled to GL | D54: 46445.229 | E54: =D54+F54/24 -> 46445.271 | F54: 1 | G54: CUT-050 | H54: James Okafor | I54: Frontier – Finance | J54: Not started | K54: FA reconciliation
... A68: CUT-066 | B68: Technical | C68: Bank integration enabled and test payment file generated | D68: 46445.458 | E68: =D68+F68/24 -> 46445.521 | F68: 1.5 | G68: CUT-063 | H68: James Okafor | I68: Frontier – Finance | J68: Not started | K68: Test payment file
A69: CUT-067 | B69: Technical | C69: ZATCA e-invoicing for ZVSA – test invoice cleared | D69: 46445.438 | E69: =D69+F69/24 -> 46445.479 | F69: 1 | G69: CUT-066 | H69: James Okafor | I69: Frontier – Finance | J69: Not started | K69: ZATCA clearance response | L69: Can start in parallel with bank test
A70: CUT-068 | B70: Technical | C70: Email-to-case and queues enabled in CE | D70: 46445.458 | E70: =D70+F70/24 -> 46445.5 | F70: 1 | G70: CUT-063 | H70: Lina Mansour | I70: Frontier – CE | J70: Not started | K70: Mailbox test
A71: CUT-069 | B71: Technical | C71: Power BI datasets refreshed against production | D71: 46445.5 | E71: =D71+F71/24 -> 46445.562 | F71: 1.5 | G71: CUT-068 | H71: James Okafor | I71: Frontier – Finance | J71: Not started | K71: Refresh history
A72: CUT-070 | B72: Technical | C72: Integration monitoring alerts enabled | D72: 46445.562 | E72: =D72+F72/24 -> 46445.604 | F72: 1 | G72: CUT-065 | H72: Arjun Mehta | I72: Frontier – Integration | J72: Not started | K72: Alert test
A73: CUT-071 | B73: Technical | C73: User access smoke test (sample of 20 users) | D73: 46445.458 | E73: =D73+F73/24 -> 46445.542 | F73: 2 | G73: CUT-063 | H73: Ravi Kumar | I73: Zava IT | J73: Not started | K73: Access test log
A74: CUT-072 | B74: Technical | C74: Warehouse mobile app connected to production | D74: 46445.542 | E74: =D74+F74/24 -> 46445.583 | F74: 1 | G74: CUT-071 | H74: Grace Lee | I74: Zava Warehouse | J74: Not started | K74: Device login test
A75: CUT-073 | B75: Technical | C75: Printing and label output tested | D75: 46445.583 | E75: =D75+F75/24 -> 46445.625 | F75: 1 | G75: CUT-072 | H75: Ravi Kumar | I75: Zava IT | J75: Not started | K75: Test labels
A76: CUT-074 | B76: Technical | C76: Technical readiness sign-off | D76: 46445.625 | E76: =D76+F76/24 -> 46445.646 | F76: 0.5 | G76: CUT-064, CUT-065, CUT-066, CUT-067, CUT-068, CUT-069, CUT-070, CUT-071, CUT-072, CUT-073 | H76: Omar Khalil | I76: Frontier – Architecture | J76: Not started | K76: Technical sign-off
A77: CUT-075 | B77: Go/No-Go gates | C77: Gate 2 pre-read: data reconciliations and technical readiness | D77: 46445.646 | E77: =D77+F77/24 -> 46445.687 | F77: 1 | G77: CUT-074 | H77: Priya Nair | I77: PMO | J77: Not started | K77: Gate 2 checklist
A78: CUT-076 | B78: Go/No-Go gates | C78: Gate 2 – Go/No-Go to start business validation | D78: 46445.688 | E78: =D78+F78/24 -> 46445.708 | F78: 0.5 | G78: CUT-075, CUT-050 | H78: Nadia Farouk | I78: Zava Sponsor | J78: Not started | K78: Gate 2 decision recorded | L78: Go/No-Go gate 2
A79: CUT-077 | B79: Business validation | C79: Finance validation – trial balances per entity | D79: 46445.708 | E79: =D79+F79/24 -> 46445.833 | F79: 3 | G79: CUT-076 | H79: Hassan Ali | I79: Zava Finance | J79: Not started | K79: Signed TB per entity
A80: CUT-078 | B80: Business validation | C80: Finance validation – open AR and AP ageing | D80: 46445.708 | E80: =D80+F80/24 -> 46445.833 | F80: 3 | G80: CUT-076 | H80: Hassan Ali | I80: Zava Finance | J80: Not started | K80: Ageing reports
A81: CUT-079 | B81: Business validation | C81: Finance validation – intercompany balances net to zero | D81: 46445.833 | E81: =D81+F81/24 -> 46445.917 | F81: 2 | G81: CUT-077 | H81: James Okafor | I81: Frontier – Finance | J81: Not started | K81: Intercompany report
A82: CUT-080 | B82: Business validation | C82: ZVSA e-invoice issued and cleared by ZATCA | D82: 46445.917 | E82: =D82+F82/24 -> 46445.958 | F82: 1 | G82: CUT-067, CUT-131 | H82: James Okafor | I82: Frontier – Finance | J82: Not started | K82: Clearance evidence
A83: CUT-081 | B83: Business validation | C83: Test AP payment run (no release to bank) | D83: 46445.833 | E83: =D83+F83/24 -> 46445.917 | F83: 2 | G83: CUT-078 | H83: Hassan Ali | I83: Zava Finance | J83: Not started | K83: Payment proposal
A84: CUT-082 | B84: Business validation | C84: Warehouse validation – receive, putaway and pick test | D84: 46445.708 | E84: =D84+F84/24 -> 46445.875 | F84: 4 | G84: CUT-076 | H84: Grace Lee | I84: Zava Warehouse | J84: Not started | K84: Test transaction list
A85: CUT-083 | B85: Business validation | C85: Warehouse validation – stock on hand spot checks (50 SKUs) | D85: 46445.875 | E85: =D85+F85/24 -> 46445.958 | F85: 2 | G85: CUT-082 | H85: Grace Lee | I85: Zava Warehouse | J85: Not started | K85: Spot check sheet
A86: CUT-084 | B86: Business validation | C86: Freight quote created with trade agreement pricing | D86: 46445.708 | E86: =D86+F86/24 -> 46445.771 | F86: 1.5 | G86: CUT-076 | H86: Lina Mansour | I86: Frontier – CE | J86: Not started | K86: Quote PDF
A87: CUT-085 | B87: Business validation | C87: Sales validation – open opportunities and quotes | D87: 46445.771 | E87: =D87+F87/24 -> 46445.854 | F87: 2 | G87: CUT-084 | H87: Lina Mansour | I87: Frontier – CE | J87: Not started | K87: Sample check sheet | L87: Zava sales validator to be confirmed
A88: CUT-086 | B88: Business validation | C88: Customer Service validation – cases, queues and SLA timers | D88: 46445.708 | E88: =D88+F88/24 -> 46445.833 | F88: 3 | G88: CUT-076 | H88: Samir Haddad | I88: Zava Customer Service | J88: Not started | K88: Case test log
A89: CUT-087 | B89: Business validation | C89: CargoWise shipment to invoice end-to-end test | D89: 46445.708 | E89: =D89+F89/24 -> 46445.833 | F89: 3 | G89: CUT-076 | H89: Arjun Mehta | I89: Frontier – Integration | J89: Not started | K89: End-to-end trace
A90: CUT-088 | B90: Business validation | C90: Power BI finance reports reviewed by Group Financial Controller | D90: 46445.833 | E90: =D90+F90/24 -> 46445.875 | F90: 1 | G90: CUT-077 | H90: Hassan Ali | I90: Zava Finance | J90: Not started | K90: Report screenshots
A91: CUT-089 | B91: Business validation | C91: Copilot in D365 and M365 features verified for pilot users | D91: 46445.708 | E91: =D91+F91/24 -> 46445.75 | F91: 1 | G91: CUT-076 | H91: Tom Becker | I91: Frontier – Change | J91: Not started | K91: Feature checklist
A92: CUT-090 | B92: Business validation | C92: Defect triage – business validation findings | D92: 46445.958 | E92: =D92+F92/24 -> 46446.042 | F92: 2 | G92: CUT-079, CUT-080, CUT-081, CUT-083, CUT-086, CUT-087, CUT-088 | H92: Priya Nair | I92: PMO | J92: Not started | K92: Defect log
A93: CUT-091 | B93: Business validation | C93: Business validation sign-off per workstream | D93: 46446.042 | E93: =D93+F93/24 -> 46446.125 | F93: 2 | G93: CUT-090 | H93: Priya Nair | I93: PMO | J93: Not started | K93: Signed validation forms
A94: CUT-092 | B94: Go/No-Go gates | C94: Gate 3 pre-read: validation sign-offs, open defects, rollback readiness | D94: 46446.125 | E94: =D94+F94/24 -> 46446.167 | F94: 1 | G94: CUT-091 | H94: Priya Nair | I94: PMO | J94: Not started | K94: Gate 3 checklist
A95: CUT-093 | B95: Go/No-Go gates | C95: Gate 3 – Final Go/No-Go decision | D95: 46446.667 | E95: =D95+F95/24 -> 46446.708 | F95: 1 | G95: CUT-092 | H95: Nadia Farouk | I95: Zava Sponsor | J95: Not started | K95: Go-live decision minutes | L95: Final Go/No-Go; rollback deadline Sun 22:00
A96: CUT-094 | B96: Go/No-Go gates | C96: Communicate Go/No-Go outcome to all stakeholders | D96: 46446.708 | E96: =D96+F96/24 -> 46446.729 | F96: 0.5 | G96: CUT-093 | H96: Elena Petrova | I96: Zava HR & Change | J96: Not started | K96: Comms email
A97: CUT-095 | B97: Go-live | C97: Open periods in D365 Finance for March 2027 (all entities) | D97: 46446.729 | E97: =D97+F97/24 -> 46446.75 | F97: 0.5 | G97: CUT-094 | H97: James Okafor | I97: Frontier – Finance | J97: Not started | K97: Period status
A98: CUT-096 | B98: Go-live | C98: Release legacy systems to archive mode | D98: 46446.729 | E98: =D98+F98/24 -> 46446.771 | F98: 1 | G98: CUT-094 | H98: Ravi Kumar | I98: Zava IT | J98: Not started | K98: Change record
A99: CUT-097 | B99: Go-live | C99: Enable all users and remove cutover restrictions | D99: 46446.75 | E99: =D99+F99/24 -> 46446.792 | F99: 1 | G99: CUT-095 | H99: Ravi Kumar | I99: Zava IT | J99: Not started | K99: Access change record
A100: CUT-098 | B100: Go-live | C100: CargoWise outbound messages resumed | D100: 46446.75 | E100: =D100+F100/24 -> 46446.771 | F100: 0.5 | G100: CUT-095 | H100: Arjun Mehta | I100: Frontier – Integration | J100: Not started | K100: Queue status
A101: CUT-099 | B101: Go-live | C101: Batch job schedule switched to production timings | D101: 46446.771 | E101: =D101+F101/24 -> 46446.792 | F101: 0.5 | G101: CUT-098 | H101: Arjun Mehta | I101: Frontier – Integration | J101: Not started | K101: Batch schedule
A102: CUT-100 | B102: Go-live | C102: Copilot licences enabled for all 600 users | D102: 46446.792 | E102: =D102+F102/24 -> 46446.833 | F102: 1 | G102: CUT-097 | H102: Tom Becker | I102: Frontier – Change | J102: Not started | K102: Licence report
A103: CUT-101 | B103: Go-live | C103: Go-live announcement to staff and customers | D103: 46447.292 | E103: =D103+F103/24 -> 46447.313 | F103: 0.5 | G103: CUT-097 | H103: Elena Petrova | I103: Zava HR & Change | J103: Not started | K103: Announcement post
A104: CUT-102 | B104: Go-live | C104: Go-live – Mon 1 Mar 2027 business open | D104: 46447.333 | E104: =D104+F104/24 -> 46447.354 | F104: 0.5 | G104: CUT-101 | H104: Nadia Farouk | I104: Zava Sponsor | J104: Not started | K104: Go-live confirmation
A105: CUT-103 | B105: Hypercare day 1 | C105: Hypercare war room opened (Jebel Ali HQ and Teams) | D105: 46447.292 | E105: =D105+F105/24 -> 46447.792 | F105: 12 | G105: CUT-095 | H105: Priya Nair | I105: PMO | J105: Not started | K105: War room log
A106: CUT-104 | B106: Hypercare day 1 | C106: First sales orders and shipments processed | D106: 46447.354 | E106: =D106+F106/24 -> 46447.479 | F106: 3 | G106: CUT-102 | H106: Lina Mansour | I106: Frontier – CE | J106: Not started | K106: Transaction list
A107: CUT-105 | B107: Hypercare day 1 | C107: First warehouse waves released and picked | D107: 46447.354 | E107: =D107+F107/24 -> 46447.479 | F107: 3 | G107: CUT-102 | H107: Grace Lee | I107: Zava Warehouse | J107: Not started | K107: Wave report
... A114: CUT-112 | B114: Hypercare day 1 | C114: Day 1 lessons learned and day 2 plan | D114: 46447.792 | E114: =D114+F114/24 -> 46447.833 | F114: 1 | G114: CUT-111 | H114: Priya Nair | I114: PMO | J114: Not started | K114: Day 2 plan

Sheet Phase summary
A1: ZAV-HZN cutover phase summary | Fictitious test data – Copilot for Frontier Consultancy scenario testing
A2: Phase | B2: Tasks | C2: Earliest start | D2: Latest finish | E2: Total task hours | F2: Elapsed hours
A3: Pre-cutover (T-14 to T-1) | B3: =COUNTIFS('Runbook'!$B$3:$B$114,A3) -> 28 | C3: =_xlfn.MINIFS('Runbook'!$D$3:$D$114,'Runbook'!$B$3:$B$114,A3) -> 46430.375 | D3: =_xlfn.MAXIFS('Runbook'!$E$3:$E$114,'Runbook'!$B$3:$B$114,A3) -> 46443.458 | E3: =SUMIFS('Runbook'!$F$3:$F$114,'Runbook'!$B$3:$B$114,A3) -> 182 | F3: =(D3-C3)*24 -> 314
A4: Freeze | B4: =COUNTIFS('Runbook'!$B$3:$B$114,A4) -> 10 | C4: =_xlfn.MINIFS('Runbook'!$D$3:$D$114,'Runbook'!$B$3:$B$114,A4) -> 46444.5 | D4: =_xlfn.MAXIFS('Runbook'!$E$3:$E$114,'Runbook'!$B$3:$B$114,A4) -> 46444.813 | E4: =SUMIFS('Runbook'!$F$3:$F$114,'Runbook'!$B$3:$B$114,A4) -> 14.5 | F4: =(D4-C4)*24 -> 7.500008
A5: Data migration | B5: =COUNTIFS('Runbook'!$B$3:$B$114,A5) -> 22 | C5: =_xlfn.MINIFS('Runbook'!$D$3:$D$114,'Runbook'!$B$3:$B$114,A5) -> 46444.854 | D5: =_xlfn.MAXIFS('Runbook'!$E$3:$E$114,'Runbook'!$B$3:$B$114,A5) -> 46445.417 | E5: =SUMIFS('Runbook'!$F$3:$F$114,'Runbook'!$B$3:$B$114,A5) -> 41.5 | F5: =(D5-C5)*24 -> 13.499992
A6: Technical | B6: =COUNTIFS('Runbook'!$B$3:$B$114,A6) -> 12 | C6: =_xlfn.MINIFS('Runbook'!$D$3:$D$114,'Runbook'!$B$3:$B$114,A6) -> 46445.417 | D6: =_xlfn.MAXIFS('Runbook'!$E$3:$E$114,'Runbook'!$B$3:$B$114,A6) -> 46445.646 | E6: =SUMIFS('Runbook'!$F$3:$F$114,'Runbook'!$B$3:$B$114,A6) -> 14 | F6: =(D6-C6)*24 -> 5.499992
A7: Business validation | B7: =COUNTIFS('Runbook'!$B$3:$B$114,A7) -> 15 | C7: =_xlfn.MINIFS('Runbook'!$D$3:$D$114,'Runbook'!$B$3:$B$114,A7) -> 46445.708 | D7: =_xlfn.MAXIFS('Runbook'!$E$3:$E$114,'Runbook'!$B$3:$B$114,A7) -> 46446.125 | E7: =SUMIFS('Runbook'!$F$3:$F$114,'Runbook'!$B$3:$B$114,A7) -> 32.5 | F7: =(D7-C7)*24 -> 10.000016
A8: Go/No-Go gates | B8: =COUNTIFS('Runbook'!$B$3:$B$114,A8) -> 7 | C8: =_xlfn.MINIFS('Runbook'!$D$3:$D$114,'Runbook'!$B$3:$B$114,A8) -> 46444.812 | D8: =_xlfn.MAXIFS('Runbook'!$E$3:$E$114,'Runbook'!$B$3:$B$114,A8) -> 46446.729 | E8: =SUMIFS('Runbook'!$F$3:$F$114,'Runbook'!$B$3:$B$114,A8) -> 5 | F8: =(D8-C8)*24 -> 45.999992
A9: Go-live | B9: =COUNTIFS('Runbook'!$B$3:$B$114,A9) -> 8 | C9: =_xlfn.MINIFS('Runbook'!$D$3:$D$114,'Runbook'!$B$3:$B$114,A9) -> 46446.729 | D9: =_xlfn.MAXIFS('Runbook'!$E$3:$E$114,'Runbook'!$B$3:$B$114,A9) -> 46447.354 | E9: =SUMIFS('Runbook'!$F$3:$F$114,'Runbook'!$B$3:$B$114,A9) -> 5.5 | F9: =(D9-C9)*24 -> 14.999984
A10: Hypercare day 1 | B10: =COUNTIFS('Runbook'!$B$3:$B$114,A10) -> 10 | C10: =_xlfn.MINIFS('Runbook'!$D$3:$D$114,'Runbook'!$B$3:$B$114,A10) -> 46447.292 | D10: =_xlfn.MAXIFS('Runbook'!$E$3:$E$114,'Runbook'!$B$3:$B$114,A10) -> 46447.833 | E10: =SUMIFS('Runbook'!$F$3:$F$114,'Runbook'!$B$3:$B$114,A10) -> 41 | F10: =(D10-C10)*24 -> 13
A11: Total | B11: =SUM(B3:B10) -> 112 | C11: =MIN(C3:C10) -> 46430.375 | D11: =MAX(D3:D10) -> 46447.833 | E11: =SUM(E3:E10) -> 336 | F11: =(D11-C11)*24 -> 419.00001
