Workbook
Name AsOfDate: 'Read me'!$B$7

Sheet Read me
A1: ZAV-HZN RAID Log
A2: Fictitious test data – Copilot for Frontier Consultancy scenario testing
A4: Purpose | B4: Risks, Assumptions, Issues and Dependencies register for the Zava Horizon programme. Use for testing Copilot Cowork scenarios such as RAID summaries, stale-item chasing, overdue reviews and SteerCo preparation.
A5: Programme | B5: Zava Horizon (ZAV-HZN) – Zava LLC, delivered by Frontier Consulting
A6: Data as of | B6: Monday 19 Oct 2026 (Dubai, UTC+4)
A7: As-of date (used in formulas) | B7: 46314
A8: Currency | B8: AED
A9: Prepared by | B9: Priya Nair, Project Manager (Frontier Consulting) – scenario owner Lorette Roos
A11: Sheet | B11: Contents
A12: RAID Log | B12: 36 RAID entries with owner, dates, probability/impact, RAG, status and mitigation. 'Days since update' and 'Stale / overdue flag' are calculated against the as-of date above.
A13: Summary | B13: Counts by type, RAG and status, plus stale and overdue counts (formulas).
A15: Rules | B15: Stale = open item not updated for more than 21 days. Overdue = open item with due date before the as-of date.
A17: Important | B17: Fictitious test data – Copilot for Frontier Consultancy scenario testing. All companies, people and figures are fictitious and must not be used for real decisions.

Sheet RAID Log
A1: ZAV-HZN RAID Log | Fictitious test data – Copilot for Frontier Consultancy scenario testing
A2: ID | B2: Type | C2: Title | D2: Description | E2: Workstream | F2: Owner | G2: Raised date | H2: Due date | I2: Probability | J2: Impact | K2: RAG | L2: Status | M2: Mitigation/Next step | N2: Last updated | O2: Days since update | P2: Stale / overdue flag
A3: R-001 | B3: Risk | C3: CargoWise API delay pushes Integration build into SIT | D3: Late vendor API specification means CargoWise shipment and invoice interfaces cannot be completed in Build; risk that SIT (30 Nov–18 Dec) starts without end-to-end freight flows. | E3: Integration | F3: Arjun Mehta | G3: 46280 | H3: 46325 | I3: High | J3: High | K3: RED | L3: Open | M3: Escalated to CargoWise account manager via Ravi Kumar; build against draft spec with mock service; re-plan Sprint 5 if spec not received by 23 Oct. | N3: 46311 | O3: =IF(L3="Closed","",AsOfDate-N3) -> 3 | P3: =IF(L3="Closed","",IF(AND(H3<AsOfDate,AsOfDate-N3>21),"Overdue & stale",IF(H3<AsOfDate,"Overdue",IF(AsOfDate-N3>21,"Stale",""))))
A4: R-002 | B4: Risk | C4: Reduced Finance SME availability during UAT | D4: UAT (11–29 Jan 2027) overlaps ZVQA year-end close; Hassan Ali's team may not be able to execute finance UAT scripts. | E4: PMO | F4: Priya Nair | G4: 46287 | H4: 46332 | I4: Medium | J4: High | K4: AMBER | L4: Open | M4: Options paper for SteerCo 28 Oct: split UAT into two waves or bring ZVQA scripts forward to SIT week 3. | N4: 46308 | O4: =IF(L4="Closed","",AsOfDate-N4) -> 6 | P4: =IF(L4="Closed","",IF(AND(H4<AsOfDate,AsOfDate-N4>21),"Overdue & stale",IF(H4<AsOfDate,"Overdue",IF(AsOfDate-N4>21,"Stale",""))))
A5: R-003 | B5: Risk | C5: ZATCA e-invoicing ISV not selected in time for ZVSA SIT | D5: Without an ISV decision the ZVSA e-invoicing connector cannot be configured or tested before SIT; compliance risk at go-live. | E5: Finance | F5: James Okafor | G5: 46266 | H5: 46304 | I5: High | J5: High | K5: AMBER | L5: Open | M5: Shortlist of two ISVs issued to Nadia Farouk; decision requested. | N5: 46287 | O5: =IF(L5="Closed","",AsOfDate-N5) -> 27 | P5: =IF(L5="Closed","",IF(AND(H5<AsOfDate,AsOfDate-N5>21),"Overdue & stale",IF(H5<AsOfDate,"Overdue",IF(AsOfDate-N5>21,"Stale","")))) -> Overdue & stale
A6: R-004 | B6: Risk | C6: Vendor master duplicates inflate migration volume | D6: 14% duplicate vendors in legacy GP 2018 and Tally risk duplicate payments and failed migration loads. | E6: Data Migration | F6: Noura Al Hashimi | G6: 46273 | H6: 46326 | I6: Medium | J6: High | K6: AMBER | L6: Open | M6: De-duplication rules agreed; Hassan Ali's team to confirm golden records by entity. | N6: 46309 | O6: =IF(L6="Closed","",AsOfDate-N6) -> 5 | P6: =IF(L6="Closed","",IF(AND(H6<AsOfDate,AsOfDate-N6>21),"Overdue & stale",IF(H6<AsOfDate,"Overdue",IF(AsOfDate-N6>21,"Stale",""))))
A7: R-005 | B7: Risk | C7: Warehouse mobile device decision delays WMS testing | D7: No decision on handheld devices; warehouse mobile app flows cannot be tested on target hardware. | E7: Supply Chain/Warehousing | F7: Rahul Verma | G7: 46275 | H7: 46297 | I7: Medium | J7: Medium | K7: AMBER | L7: Open | M7: Device comparison sent to Grace Lee; awaiting decision. | N7: 46283 | O7: =IF(L7="Closed","",AsOfDate-N7) -> 31 | P7: =IF(L7="Closed","",IF(AND(H7<AsOfDate,AsOfDate-N7>21),"Overdue & stale",IF(H7<AsOfDate,"Overdue",IF(AsOfDate-N7>21,"Stale","")))) -> Overdue & stale
A8: R-006 | B8: Risk | C8: Programme spend ahead of plan | D8: Spend to 30 Sep 2026 is AED 3.05m against plan of AED 2.85m (+7.0%); continued overrun would draw down the AED 0.6m contingency early. | E8: PMO | F8: Priya Nair | G8: 46300 | H8: 46323 | I8: Medium | J8: High | K8: AMBER | L8: Open | M8: Forecast to complete re-baselined; contingency drawdown request for CargoWise rework to SteerCo 28 Oct. | N8: 46310 | O8: =IF(L8="Closed","",AsOfDate-N8) -> 4 | P8: =IF(L8="Closed","",IF(AND(H8<AsOfDate,AsOfDate-N8>21),"Overdue & stale",IF(H8<AsOfDate,"Overdue",IF(AsOfDate-N8>21,"Stale",""))))
A9: R-007 | B9: Risk | C9: Group Financial Controller time split with BAU | D9: Hassan Ali is splitting time between BAU month-end and design walkthroughs; finance decisions are slowing. | E9: Finance | F9: James Okafor | G9: 46252 | H9: 46290 | I9: Medium | J9: Medium | K9: AMBER | L9: Open | M9: Request a delegate from Hassan Ali's team for day-to-day decisions. | N9: 46259 | O9: =IF(L9="Closed","",AsOfDate-N9) -> 55 | P9: =IF(L9="Closed","",IF(AND(H9<AsOfDate,AsOfDate-N9>21),"Overdue & stale",IF(H9<AsOfDate,"Overdue",IF(AsOfDate-N9>21,"Stale","")))) -> Overdue & stale
A10: R-008 | B10: Risk | C10: Copilot adoption stalls beyond the pilot group | D10: Weekly active usage outside the 120 pilot users may stay low once the 600 licences are assigned. | E10: Change & Copilot Adoption | F10: Tom Becker | G10: 46294 | H10: 46339 | I10: Medium | J10: Medium | K10: GREEN | L10: Open | M10: Champions network by department; persona-based training wave 2. | N10: 46307 | O10: =IF(L10="Closed","",AsOfDate-N10) -> 7 | P10: =IF(L10="Closed","",IF(AND(H10<AsOfDate,AsOfDate-N10>21),"Overdue & stale",IF(H10<AsOfDate,"Overdue",IF(AsOfDate-N10>21,"Stale",""))))
A11: R-009 | B11: Risk | C11: Oversharing exposes sensitive content through Copilot | D11: SharePoint readiness scan flags 37 of 60 sites shared with 'Everyone except external users', including HR-Payroll and Finance-Board. | E11: Change & Copilot Adoption | F11: Tom Becker | G11: 46301 | H11: 46318 | I11: High | J11: High | K11: AMBER | L11: Open | M11: Remove EEEU permissions on flagged sites; apply sensitivity labels; restricted SharePoint search for HR and Finance sites. | N11: 46311 | O11: =IF(L11="Closed","",AsOfDate-N11) -> 3 | P11: =IF(L11="Closed","",IF(AND(H11<AsOfDate,AsOfDate-N11>21),"Overdue & stale",IF(H11<AsOfDate,"Overdue",IF(AsOfDate-N11>21,"Stale",""))))
A12: R-010 | B12: Risk | C12: Pricing accuracy risk from CR-009 | D12: Replacing the bespoke rate-card engine with standard trade agreements saves 12 days but may not reproduce all surcharge rules. | E12: Sales & Service CE | F12: Lina Mansour | G12: 46302 | H12: 46323 | I12: Medium | J12: High | K12: AMBER | L12: Open | M12: Run 200 historical quotes through trade agreements and compare before SteerCo decision. | N12: 46309 | O12: =IF(L12="Closed","",AsOfDate-N12) -> 5 | P12: =IF(L12="Closed","",IF(AND(H12<AsOfDate,AsOfDate-N12>21),"Overdue & stale",IF(H12<AsOfDate,"Overdue",IF(AsOfDate-N12>21,"Stale",""))))
A13: R-011 | B13: Risk | C13: Tally (KSA) extraction quality for opening balances | D13: Tally exports for ZVSA lack dimension detail; opening balance load may need manual mapping. | E13: Data Migration | F13: Noura Al Hashimi | G13: 46254 | H13: 46310 | I13: Medium | J13: Medium | K13: GREEN | L13: Open | M13: Mapping workbook with ZVSA finance team. | N13: 46268 | O13: =IF(L13="Closed","",AsOfDate-N13) -> 46 | P13: =IF(L13="Closed","",IF(AND(H13<AsOfDate,AsOfDate-N13>21),"Overdue & stale",IF(H13<AsOfDate,"Overdue",IF(AsOfDate-N13>21,"Stale","")))) -> Overdue & stale
A14: R-012 | B14: Risk | C14: Case queue design misaligned with shift model | D14: Customer Service queues did not reflect Samir Haddad's three-shift model. | E14: Sales & Service CE | F14: Lina Mansour | G14: 46259 | H14: 46283 | I14: Low | J14: Medium | K14: GREEN | L14: Closed | M14: Queue design reworked and signed off by Samir Haddad. | N14: 46283 | O14: =IF(L14="Closed","",AsOfDate-N14) | P14: =IF(L14="Closed","",IF(AND(H14<AsOfDate,AsOfDate-N14>21),"Overdue & stale",IF(H14<AsOfDate,"Overdue",IF(AsOfDate-N14>21,"Stale",""))))
... A38: D-006 | B38: Dependency | C38: Entra ID groups and Conditional Access for Copilot | D38: Copilot rollout depends on licence groups and Conditional Access policies. | E38: Change & Copilot Adoption | F38: Tom Becker | G38: 46266 | H38: 46295 | I38: Low | J38: Medium | K38: GREEN | L38: Closed | M38: Configured by Zava IT. | N38: 46294 | O38: =IF(L38="Closed","",AsOfDate-N38) | P38: =IF(L38="Closed","",IF(AND(H38<AsOfDate,AsOfDate-N38>21),"Overdue & stale",IF(H38<AsOfDate,"Overdue",IF(AsOfDate-N38>21,"Stale",""))))

Sheet Summary
A1: ZAV-HZN RAID summary | Fictitious test data – Copilot for Frontier Consultancy scenario testing
A2: Type | B2: Total | C2: Open | D2: RED (open) | E2: AMBER (open) | F2: GREEN (open) | G2: Overdue (open) | H2: Stale (open)
A3: Risk | B3: =COUNTIFS('RAID Log'!$B$3:$B$38,A3) -> 14 | C3: =COUNTIFS('RAID Log'!$B$3:$B$38,A3,'RAID Log'!$L$3:$L$38,"Open") -> 13 | D3: =COUNTIFS('RAID Log'!$B$3:$B$38,$A3,'RAID Log'!$L$3:$L$38,"Open",'RAID Log'!$K$3:$K$38,"RED") -> 1 | E3: =COUNTIFS('RAID Log'!$B$3:$B$38,$A3,'RAID Log'!$L$3:$L$38,"Open",'RAID Log'!$K$3:$K$38,"AMBER") -> 9 | F3: =COUNTIFS('RAID Log'!$B$3:$B$38,$A3,'RAID Log'!$L$3:$L$38,"Open",'RAID Log'!$K$3:$K$38,"GREEN") -> 3 | G3: =COUNTIFS('RAID Log'!$B$3:$B$38,A3,'RAID Log'!$P$3:$P$38,"Overdue*") -> 4 | H3: =COUNTIFS('RAID Log'!$B$3:$B$38,A3,'RAID Log'!$P$3:$P$38,"*stale*") -> 4
A4: Assumption | B4: =COUNTIFS('RAID Log'!$B$3:$B$38,A4) -> 7 | C4: =COUNTIFS('RAID Log'!$B$3:$B$38,A4,'RAID Log'!$L$3:$L$38,"Open") -> 6 | D4: =COUNTIFS('RAID Log'!$B$3:$B$38,$A4,'RAID Log'!$L$3:$L$38,"Open",'RAID Log'!$K$3:$K$38,"RED") -> 0 | E4: =COUNTIFS('RAID Log'!$B$3:$B$38,$A4,'RAID Log'!$L$3:$L$38,"Open",'RAID Log'!$K$3:$K$38,"AMBER") -> 3 | F4: =COUNTIFS('RAID Log'!$B$3:$B$38,$A4,'RAID Log'!$L$3:$L$38,"Open",'RAID Log'!$K$3:$K$38,"GREEN") -> 3 | G4: =COUNTIFS('RAID Log'!$B$3:$B$38,A4,'RAID Log'!$P$3:$P$38,"Overdue*") -> 2 | H4: =COUNTIFS('RAID Log'!$B$3:$B$38,A4,'RAID Log'!$P$3:$P$38,"*stale*") -> 3
A5: Issue | B5: =COUNTIFS('RAID Log'!$B$3:$B$38,A5) -> 9 | C5: =COUNTIFS('RAID Log'!$B$3:$B$38,A5,'RAID Log'!$L$3:$L$38,"Open") -> 8 | D5: =COUNTIFS('RAID Log'!$B$3:$B$38,$A5,'RAID Log'!$L$3:$L$38,"Open",'RAID Log'!$K$3:$K$38,"RED") -> 1 | E5: =COUNTIFS('RAID Log'!$B$3:$B$38,$A5,'RAID Log'!$L$3:$L$38,"Open",'RAID Log'!$K$3:$K$38,"AMBER") -> 7 | F5: =COUNTIFS('RAID Log'!$B$3:$B$38,$A5,'RAID Log'!$L$3:$L$38,"Open",'RAID Log'!$K$3:$K$38,"GREEN") -> 0 | G5: =COUNTIFS('RAID Log'!$B$3:$B$38,A5,'RAID Log'!$P$3:$P$38,"Overdue*") -> 3 | H5: =COUNTIFS('RAID Log'!$B$3:$B$38,A5,'RAID Log'!$P$3:$P$38,"*stale*") -> 2
A6: Dependency | B6: =COUNTIFS('RAID Log'!$B$3:$B$38,A6) -> 6 | C6: =COUNTIFS('RAID Log'!$B$3:$B$38,A6,'RAID Log'!$L$3:$L$38,"Open") -> 5 | D6: =COUNTIFS('RAID Log'!$B$3:$B$38,$A6,'RAID Log'!$L$3:$L$38,"Open",'RAID Log'!$K$3:$K$38,"RED") -> 1 | E6: =COUNTIFS('RAID Log'!$B$3:$B$38,$A6,'RAID Log'!$L$3:$L$38,"Open",'RAID Log'!$K$3:$K$38,"AMBER") -> 4 | F6: =COUNTIFS('RAID Log'!$B$3:$B$38,$A6,'RAID Log'!$L$3:$L$38,"Open",'RAID Log'!$K$3:$K$38,"GREEN") -> 0 | G6: =COUNTIFS('RAID Log'!$B$3:$B$38,A6,'RAID Log'!$P$3:$P$38,"Overdue*") -> 1 | H6: =COUNTIFS('RAID Log'!$B$3:$B$38,A6,'RAID Log'!$P$3:$P$38,"*stale*") -> 2
A7: Total | B7: =SUM(B3:B6) -> 36 | C7: =SUM(C3:C6) -> 32 | D7: =SUM(D3:D6) -> 3 | E7: =SUM(E3:E6) -> 23 | F7: =SUM(F3:F6) -> 6 | G7: =SUM(G3:G6) -> 10 | H7: =SUM(H3:H6) -> 11
A9: Check: total entries on RAID Log (should equal B7) | B9: =COUNTA('RAID Log'!$A$3:$A$38) -> 36
