Workbook
Name AsOfDate: 'Read me'!$B$7

Sheet Read me
A1: ZAV-HZN Sprint Backlog Export
A2: Fictitious test data – Copilot for Frontier Consultancy scenario testing
A4: Purpose | B4: Azure DevOps-style work item export for the Zava Horizon Build phase (Sprints 3–5). Use for testing sprint status summaries, blocker analysis (CargoWise), velocity and burndown questions, and stand-up preparation.
A5: Programme | B5: Zava Horizon (ZAV-HZN) – Zava LLC, delivered by Frontier Consulting
A6: Data as of | B6: Monday 19 Oct 2026 (Dubai, UTC+4)
A7: As-of date (used in formulas) | B7: 46314
A8: Currency | B8: AED
A9: Prepared by | B9: Priya Nair, Project Manager (Frontier Consulting) – scenario owner Lorette Roos
A11: Sheet | B11: Contents
A12: Backlog | B12: 90 work items (Epics, Features, User Stories, Bugs, Tasks) exported from Azure DevOps project ZAV-HZN. Epics and Features sit at release level.
A13: Sprint summary | B13: Story points and item counts by sprint and state, Sprint 4 completion % and blocked counts (formulas).
A15: Sprint calendar | B15: Sprint 3: Mon 28 Sep – Fri 9 Oct 2026 | Sprint 4: Mon 12 Oct – Fri 23 Oct 2026 | Sprint 5: Mon 26 Oct – Fri 6 Nov 2026
A16: Completion rule | B16: Completed = State Resolved or Closed; completion % measured on story points.
A18: Important | B18: Fictitious test data – Copilot for Frontier Consultancy scenario testing. All companies, people and figures are fictitious and must not be used for real decisions.

Sheet Backlog
A1: ZAV-HZN Sprint Backlog Export (Azure DevOps) | Fictitious test data – Copilot for Frontier Consultancy scenario testing
A2: ID | B2: Work item type | C2: Title | D2: Workstream | E2: Assigned to | F2: State | G2: Sprint | H2: Story points | I2: Remaining work | J2: Tags | K2: Changed date
A3: 4101 | B3: Epic | C3: Finance core – GL, AP, AR, fixed assets for five legal entities | D3: Finance | E3: James Okafor | F3: Active | G3: ZAV-HZN\Release 1 | J3: fin | K3: 46300.425
A4: 4102 | B4: Epic | C4: Warehouse management and transport for Jebel Ali operations | D4: Supply Chain/Warehousing | E4: Rahul Verma | F4: Active | G4: ZAV-HZN\Release 1 | J4: scm | K4: 46300.425
A5: 4103 | B5: Epic | C5: Sales and Customer Service on Dynamics 365 CE | D5: Sales & Service CE | E5: Lina Mansour | F5: Active | G5: ZAV-HZN\Release 1 | J5: ce | K5: 46300.425
A6: 4104 | B6: Epic | C6: Data migration from Dynamics GP 2018 and Tally | D6: Data Migration | E6: Noura Al Hashimi | F6: Active | G6: ZAV-HZN\Release 1 | J6: dm | K6: 46300.425
A7: 4105 | B7: Epic | C7: Integrations – CargoWise, banks, ZATCA, Azure Integration Services | D7: Integration | E7: Arjun Mehta | F7: Active | G7: ZAV-HZN\Release 1 | J7: int | K7: 46300.425
A8: 4106 | B8: Epic | C8: M365 Copilot rollout – 600 licences | D8: Change & Copilot Adoption | E8: Tom Becker | F8: Active | G8: ZAV-HZN\Release 1 | J8: chg | K8: 46300.425
A9: 4107 | B9: Feature | C9: Intercompany accounting ZVAE/ZVSA/ZVOM/ZVQA/ZVHQ | D9: Finance | E9: James Okafor | F9: Active | G9: ZAV-HZN\Release 1 | J9: fin | K9: 46303.653
A10: 4108 | B10: Feature | C10: ZATCA e-invoicing for ZVSA | D10: Finance | E10: James Okafor | F10: Active | G10: ZAV-HZN\Release 1 | J10: fin | K10: 46303.653
A11: 4109 | B11: Feature | C11: Bank statement and payment integration | D11: Finance | E11: James Okafor | F11: Active | G11: ZAV-HZN\Release 1 | J11: fin | K11: 46303.653
A12: 4110 | B12: Feature | C12: Mobile warehouse app – receiving and putaway | D12: Supply Chain/Warehousing | E12: Rahul Verma | F12: Active | G12: ZAV-HZN\Release 1 | J12: scm | K12: 46303.653
A13: 4111 | B13: Feature | C13: Trade agreements and freight rate cards | D13: Supply Chain/Warehousing | E13: Rahul Verma | F13: Active | G13: ZAV-HZN\Release 1 | J13: scm | K13: 46303.653
A14: 4112 | B14: Feature | C14: Lead-to-quote for freight forwarding | D14: Sales & Service CE | E14: Lina Mansour | F14: Active | G14: ZAV-HZN\Release 1 | J14: ce | K14: 46303.653
... A22: 4120 | B22: Feature | C22: Financial reporting and Power BI | D22: Finance | E22: James Okafor | F22: New | G22: ZAV-HZN\Release 1 | J22: fin | K22: 46303.653
A23: 4121 | B23: User Story | C23: GL chart of accounts and main account structure for ZVAE | D23: Finance | E23: James Okafor | F23: Closed | G23: ZAV-HZN\Sprint 3 | H23: 5 | J23: fin | K23: 46296.375
A24: 4122 | B24: User Story | C24: Financial dimensions: entity, department, cost centre, trade lane | D24: Finance | E24: James Okafor | F24: Closed | G24: ZAV-HZN\Sprint 3 | H24: 3 | J24: fin | K24: 46297.422
A25: 4123 | B25: User Story | C25: AP invoice approval workflow with 3-way match | D25: Finance | E25: James Okafor | F25: Closed | G25: ZAV-HZN\Sprint 3 | H25: 5 | J25: fin | K25: 46298.468
A26: 4124 | B26: Task | C26: Configure number sequences for five legal entities | D26: Finance | E26: Arjun Mehta | F26: Closed | G26: ZAV-HZN\Sprint 3 | I26: 0 | J26: fin | K26: 46299.515
A27: 4125 | B27: User Story | C27: Warehouse locations and zones for Jebel Ali DC | D27: Supply Chain/Warehousing | E27: Rahul Verma | F27: Closed | G27: ZAV-HZN\Sprint 3 | H27: 5 | J27: scm | K27: 46300.561
A28: 4126 | B28: User Story | C28: Inbound receiving by license plate | D28: Supply Chain/Warehousing | E28: Rahul Verma | F28: Closed | G28: ZAV-HZN\Sprint 3 | H28: 8 | J28: scm | K28: 46301.608
A29: 4127 | B29: Bug | C29: Location directive picks wrong zone for bonded stock | D29: Supply Chain/Warehousing | E29: Rahul Verma | F29: Closed | G29: ZAV-HZN\Sprint 3 | H29: 2 | J29: scm | K29: 46302.654
A30: 4128 | B30: User Story | C30: Account and contact model for shippers and consignees | D30: Sales & Service CE | E30: Lina Mansour | F30: Closed | G30: ZAV-HZN\Sprint 3 | H30: 3 | J30: ce | K30: 46303.701
A31: 4129 | B31: User Story | C31: Opportunity stages for freight forwarding deals | D31: Sales & Service CE | E31: Lina Mansour | F31: Closed | G31: ZAV-HZN\Sprint 3 | H31: 3 | J31: ce | K31: 46304.414
A32: 4130 | B32: User Story | C32: Case categories and queues for three-shift model | D32: Sales & Service CE | E32: Lina Mansour | F32: Closed | G32: ZAV-HZN\Sprint 3 | H32: 5 | J32: ce | K32: 46296.419
A33: 4131 | B33: Task | C33: SLA KPI configuration for first response | D33: Sales & Service CE | E33: Lina Mansour | F33: Resolved | G33: ZAV-HZN\Sprint 3 | I33: 0 | J33: ce | K33: 46297.465
A34: 4132 | B34: User Story | C34: Vendor master profiling – GP 2018 and Tally | D34: Data Migration | E34: Noura Al Hashimi | F34: Closed | G34: ZAV-HZN\Sprint 3 | H34: 5 | J34: dm | K34: 46298.512
A35: 4133 | B35: Task | C35: Data migration framework – staging database | D35: Data Migration | E35: Noura Al Hashimi | F35: Closed | G35: ZAV-HZN\Sprint 3 | I35: 0 | J35: dm | K35: 46299.558
A36: 4134 | B36: User Story | C36: Customer master mapping template | D36: Data Migration | E36: Noura Al Hashimi | F36: Closed | G36: ZAV-HZN\Sprint 3 | H36: 3 | J36: dm | K36: 46300.605
A37: 4135 | B37: User Story | C37: Azure Service Bus topics and subscriptions | D37: Integration | E37: Arjun Mehta | F37: Closed | G37: ZAV-HZN\Sprint 3 | H37: 5 | J37: int | K37: 46301.651
A38: 4136 | B38: Task | C38: Key Vault and managed identity setup | D38: Integration | E38: Arjun Mehta | F38: Closed | G38: ZAV-HZN\Sprint 3 | I38: 0 | J38: int | K38: 46302.698
A39: 4137 | B39: User Story | C39: CargoWise interface design (draft spec) | D39: Integration | E39: Arjun Mehta | F39: Resolved | G39: ZAV-HZN\Sprint 3 | H39: 5 | J39: int | K39: 46303.411
A40: 4138 | B40: User Story | C40: Copilot pilot onboarding – 120 users | D40: Change & Copilot Adoption | E40: Tom Becker | F40: Closed | G40: ZAV-HZN\Sprint 3 | H40: 3 | J40: chg | K40: 46304.458
A41: 4139 | B41: User Story | C41: SharePoint oversharing scan – 60 sites | D41: Change & Copilot Adoption | E41: Tom Becker | F41: Closed | G41: ZAV-HZN\Sprint 3 | H41: 3 | J41: chg | K41: 46296.463
A42: 4140 | B42: Bug | C42: Posting profile error on ZVOM vendor invoices | D42: Finance | E42: James Okafor | F42: Closed | G42: ZAV-HZN\Sprint 3 | H42: 2 | J42: fin | K42: 46297.509
A43: 4141 | B43: Task | C43: Sprint 3 demo and retrospective | D43: Finance | E43: Priya Nair | F43: Closed | G43: ZAV-HZN\Sprint 3 | I43: 0 | J43: fin | K43: 46298.556
A44: 4142 | B44: User Story | C44: Fixed asset groups and depreciation profiles | D44: Finance | E44: James Okafor | F44: Closed | G44: ZAV-HZN\Sprint 3 | H44: 5 | J44: fin | K44: 46299.602
A45: 4143 | B45: User Story | C45: Intercompany journal auto-posting ZVAE to ZVSA | D45: Finance | E45: James Okafor | F45: Closed | G45: ZAV-HZN\Sprint 4 | H45: 8 | I45: 0 | J45: fin; intercompany | K45: 46307.375
A46: 4144 | B46: User Story | C46: Intercompany due-to/due-from settlement rules | D46: Finance | E46: James Okafor | F46: Closed | G46: ZAV-HZN\Sprint 4 | H46: 5 | I46: 0 | J46: fin; intercompany | K46: 46308.426
A47: 4145 | B47: User Story | C47: AR customer invoicing with freight charge codes | D47: Finance | E47: James Okafor | F47: Closed | G47: ZAV-HZN\Sprint 4 | H47: 8 | I47: 0 | J47: fin | K47: 46309.476
A48: 4146 | B48: User Story | C48: Bank reconciliation – UAE statement import | D48: Finance | E48: James Okafor | F48: Resolved | G48: ZAV-HZN\Sprint 4 | H48: 5 | I48: 0 | J48: fin; banking | K48: 46310.527
A49: 4147 | B49: Bug | C49: Exchange rate revaluation posts to wrong account (ZVQA) | D49: Finance | E49: James Okafor | F49: Closed | G49: ZAV-HZN\Sprint 4 | H49: 2 | I49: 0 | J49: fin; ZVQA | K49: 46311.578
A50: 4148 | B50: User Story | C50: Wave picking for outbound shipments | D50: Supply Chain/Warehousing | E50: Rahul Verma | F50: Closed | G50: ZAV-HZN\Sprint 4 | H50: 8 | I50: 0 | J50: scm; WMS | K50: 46311.587
A51: 4149 | B51: User Story | C51: Cycle counting by zone | D51: Supply Chain/Warehousing | E51: Rahul Verma | F51: Resolved | G51: ZAV-HZN\Sprint 4 | H51: 5 | I51: 0 | J51: scm; WMS | K51: 46311.637
A52: 4150 | B52: User Story | C52: Trade agreement journals for standard freight rates | D52: Supply Chain/Warehousing | E52: Rahul Verma | F52: Closed | G52: ZAV-HZN\Sprint 4 | H52: 5 | I52: 0 | J52: scm; CR-009 | K52: 46314.688
A53: 4151 | B53: User Story | C53: Quote template with freight rate lines | D53: Sales & Service CE | E53: Lina Mansour | F53: Closed | G53: ZAV-HZN\Sprint 4 | H53: 5 | I53: 0 | J53: ce | K53: 46307.739
A54: 4152 | B54: User Story | C54: Case routing by entity and language (Arabic/English) | D54: Sales & Service CE | E54: Lina Mansour | F54: Closed | G54: ZAV-HZN\Sprint 4 | H54: 5 | I54: 0 | J54: ce | K54: 46308.415
A55: 4153 | B55: User Story | C55: SLA escalation to Customer Service Manager | D55: Sales & Service CE | E55: Lina Mansour | F55: Closed | G55: ZAV-HZN\Sprint 4 | H55: 3 | I55: 0 | J55: ce | K55: 46309.424
A56: 4154 | B56: User Story | C56: Vendor de-duplication rules (14% duplicates) | D56: Data Migration | E56: Noura Al Hashimi | F56: Closed | G56: ZAV-HZN\Sprint 4 | H56: 5 | I56: 0 | J56: dm; vendor-dedup | K56: 46310.474
... A59: 4157 | B59: User Story | C59: Copilot prompt gallery for Finance analyst persona | D59: Change & Copilot Adoption | E59: Tom Becker | F59: Closed | G59: ZAV-HZN\Sprint 4 | H59: 2 | I59: 0 | J59: chg; copilot | K59: 46311.585
A60: 4158 | B60: User Story | C60: Mobile app receiving on handheld | D60: Supply Chain/Warehousing | E60: Rahul Verma | F60: Active | G60: ZAV-HZN\Sprint 4 | H60: 3 | J60: scm; WMS; device-decision | K60: 46314.635
A61: 4159 | B61: User Story | C61: Power BI finance dataset – trial balance | D61: Finance | E61: James Okafor | F61: Active | G61: ZAV-HZN\Sprint 4 | H61: 2 | J61: fin; reporting | K61: 46307.686
A62: 4160 | B62: Bug | C62: Case SLA timer pauses incorrectly on weekends | D62: Sales & Service CE | E62: Lina Mansour | F62: Active | G62: ZAV-HZN\Sprint 4 | H62: 1 | J62: ce | K62: 46308.737
A63: 4161 | B63: User Story | C63: Remove EEEU permissions on flagged SharePoint sites | D63: Change & Copilot Adoption | E63: Tom Becker | F63: New | G63: ZAV-HZN\Sprint 4 | H63: 3 | J63: chg; copilot; oversharing | K63: 46309.412
A64: 4162 | B64: User Story | C64: Copilot champions network setup | D64: Change & Copilot Adoption | E64: Tom Becker | F64: New | G64: ZAV-HZN\Sprint 4 | H64: 3 | J64: chg; copilot | K64: 46310.422
A65: 4163 | B65: User Story | C65: CargoWise shipment event inbound interface | D65: Integration | E65: Arjun Mehta | F65: Blocked | G65: ZAV-HZN\Sprint 4 | H65: 5 | J65: int; CargoWise; Blocked; vendor-spec | K65: 46311.528
A66: 4164 | B66: User Story | C66: CargoWise job costing to F&O project accounting | D66: Integration | E66: Arjun Mehta | F66: Blocked | G66: ZAV-HZN\Sprint 4 | H66: 5 | J66: int; CargoWise; Blocked; vendor-spec | K66: 46309.577
A67: 4165 | B67: User Story | C67: CargoWise AR invoice sync to D365 Finance | D67: Integration | E67: Arjun Mehta | F67: Blocked | G67: ZAV-HZN\Sprint 4 | H67: 5 | J67: int; CargoWise; Blocked; vendor-spec | K67: 46310.585
A68: 4166 | B68: User Story | C68: Customer account sync D365 CE to CargoWise | D68: Integration | E68: Arjun Mehta | F68: Blocked | G68: ZAV-HZN\Sprint 4 | H68: 3 | J68: int; CargoWise; Blocked; vendor-spec | K68: 46311.634
A69: 4167 | B69: Task | C69: Build CargoWise API mock service | D69: Integration | E69: Arjun Mehta | F69: Blocked | G69: ZAV-HZN\Sprint 4 | I69: 16 | J69: int; CargoWise; Blocked | K69: 46309.433
A70: 4168 | B70: Task | C70: CargoWise error handling and retry policy | D70: Integration | E70: Arjun Mehta | F70: Blocked | G70: ZAV-HZN\Sprint 4 | I70: 12 | J70: int; CargoWise; Blocked | K70: 46310.483
A71: 4169 | B71: Task | C71: Bank payment file format – KSA | D71: Finance | E71: Arjun Mehta | F71: Active | G71: ZAV-HZN\Sprint 4 | I71: 6 | J71: fin; banking | K71: 46309.735
A72: 4170 | B72: Task | C72: Sprint 4 demo preparation | D72: Finance | E72: Priya Nair | F72: New | G72: ZAV-HZN\Sprint 4 | I72: 4 | J72: fin | K72: 46310.41
A73: 4171 | B73: User Story | C73: ZATCA e-invoicing connector configuration (pending ISV) | D73: Finance | E73: James Okafor | F73: New | G73: ZAV-HZN\Sprint 5 | H73: 5 | J73: fin; ZATCA; ZVSA | K73: 46300.375
A74: 4172 | B74: User Story | C74: Intercompany auto-settlement for ZVQA (CR-007, pending approval) | D74: Finance | E74: James Okafor | F74: New | G74: ZAV-HZN\Sprint 5 | H74: 8 | J74: fin; CR-007; ZVQA | K74: 46301.428
A75: 4173 | B75: User Story | C75: Fixed asset migration template | D75: Finance | E75: James Okafor | F75: New | G75: ZAV-HZN\Sprint 5 | H75: 3 | J75: fin | K75: 46302.482
A76: 4174 | B76: User Story | C76: Vendor payment proposal and approval | D76: Finance | E76: James Okafor | F76: New | G76: ZAV-HZN\Sprint 5 | H76: 5 | J76: fin | K76: 46303.535
A77: 4175 | B77: User Story | C77: Outbound load building and dock appointment | D77: Supply Chain/Warehousing | E77: Rahul Verma | F77: New | G77: ZAV-HZN\Sprint 5 | H77: 8 | J77: scm; WMS | K77: 46304.547
A78: 4176 | B78: User Story | C78: Replenishment templates for fast movers | D78: Supply Chain/Warehousing | E78: Rahul Verma | F78: New | G78: ZAV-HZN\Sprint 5 | H78: 5 | J78: scm; WMS | K78: 46305.601
A79: 4177 | B79: User Story | C79: Mobile app putaway on handheld | D79: Supply Chain/Warehousing | E79: Rahul Verma | F79: New | G79: ZAV-HZN\Sprint 5 | H79: 3 | J79: scm; WMS; device-decision | K79: 46306.654
A80: 4178 | B80: User Story | C80: Customer portal for shipment tracking (CR-008, pending approval) | D80: Sales & Service CE | E80: Lina Mansour | F80: New | G80: ZAV-HZN\Sprint 5 | H80: 13 | J80: ce; CR-008 | K80: 46307.708
A81: 4179 | B81: User Story | C81: Knowledge articles for top 10 case categories | D81: Sales & Service CE | E81: Lina Mansour | F81: New | G81: ZAV-HZN\Sprint 5 | H81: 3 | J81: ce | K81: 46308.386
A82: 4180 | B82: User Story | C82: Quote approval matrix by margin | D82: Sales & Service CE | E82: Lina Mansour | F82: New | G82: ZAV-HZN\Sprint 5 | H82: 5 | J82: ce | K82: 46309.44
A83: 4181 | B83: User Story | C83: Vendor master de-duplicated trial load 2 | D83: Data Migration | E83: Noura Al Hashimi | F83: New | G83: ZAV-HZN\Sprint 5 | H83: 5 | J83: dm; vendor-dedup; trial-load | K83: 46310.493
A84: 4182 | B84: User Story | C84: Open AP/AR items extraction from GP 2018 | D84: Data Migration | E84: Noura Al Hashimi | F84: New | G84: ZAV-HZN\Sprint 5 | H84: 5 | J84: dm; trial-load | K84: 46311.505
... A87: 4185 | B87: User Story | C87: Integration monitoring dashboard in Azure Monitor | D87: Integration | E87: Arjun Mehta | F87: New | G87: ZAV-HZN\Sprint 5 | H87: 3 | J87: int | K87: 46302.665
A88: 4186 | B88: Task | C88: Bank payment file format – Oman | D88: Integration | E88: Arjun Mehta | F88: New | G88: ZAV-HZN\Sprint 5 | I88: 8 | J88: int | K88: 46303.677
A89: 4187 | B89: User Story | C89: Copilot training wave 2 – Customer service agent persona | D89: Change & Copilot Adoption | E89: Tom Becker | F89: New | G89: ZAV-HZN\Sprint 5 | H89: 3 | J89: chg; copilot | K89: 46304.397
A90: 4188 | B90: User Story | C90: Sensitivity labels for HR-Payroll and Finance-Board sites | D90: Change & Copilot Adoption | E90: Tom Becker | F90: New | G90: ZAV-HZN\Sprint 5 | H90: 2 | J90: chg; copilot; oversharing | K90: 46305.451
A91: 4189 | B91: Bug | C91: Duplicate contact created on email-to-case | D91: Sales & Service CE | E91: Lina Mansour | F91: New | G91: ZAV-HZN\Sprint 5 | H91: 2 | J91: ce | K91: 46306.463
A92: 4190 | B92: Task | C92: Sprint 5 planning and capacity check | D92: Finance | E92: Priya Nair | F92: New | G92: ZAV-HZN\Sprint 5 | I92: 8 | J92: fin | K92: 46307.516

Sheet Sprint summary
A1: ZAV-HZN sprint summary | Fictitious test data – Copilot for Frontier Consultancy scenario testing
A2: Sprint | B2: Items | C2: Story points (total) | D2: Points – New | E2: Points – Active | F2: Points – Resolved | G2: Points – Closed | H2: Points – Blocked | I2: Points completed | J2: Completion % | K2: Blocked items | L2: Remaining work (h)
A3: ZAV-HZN\Sprint 3 | B3: =COUNTIFS(Backlog!$G$3:$G$92,$A3) -> 22 | C3: =SUMIFS(Backlog!$H$3:$H$92,Backlog!$G$3:$G$92,$A3) -> 70 | D3: =SUMIFS(Backlog!$H$3:$H$92,Backlog!$G$3:$G$92,$A3,Backlog!$F$3:$F$92,"New") -> 0 | E3: =SUMIFS(Backlog!$H$3:$H$92,Backlog!$G$3:$G$92,$A3,Backlog!$F$3:$F$92,"Active") -> 0 | F3: =SUMIFS(Backlog!$H$3:$H$92,Backlog!$G$3:$G$92,$A3,Backlog!$F$3:$F$92,"Resolved") -> 5 | G3: =SUMIFS(Backlog!$H$3:$H$92,Backlog!$G$3:$G$92,$A3,Backlog!$F$3:$F$92,"Closed") -> 65 | H3: =SUMIFS(Backlog!$H$3:$H$92,Backlog!$G$3:$G$92,$A3,Backlog!$F$3:$F$92,"Blocked") -> 0 | I3: =F3+G3 -> 70 | J3: =IF(C3=0,0,I3/C3) -> 1 | K3: =COUNTIFS(Backlog!$G$3:$G$92,$A3,Backlog!$F$3:$F$92,"Blocked") -> 0 | L3: =SUMIFS(Backlog!$I$3:$I$92,Backlog!$G$3:$G$92,$A3) -> 0
A4: ZAV-HZN\Sprint 4 | B4: =COUNTIFS(Backlog!$G$3:$G$92,$A4) -> 28 | C4: =SUMIFS(Backlog!$H$3:$H$92,Backlog!$G$3:$G$92,$A4) -> 100 | D4: =SUMIFS(Backlog!$H$3:$H$92,Backlog!$G$3:$G$92,$A4,Backlog!$F$3:$F$92,"New") -> 6 | E4: =SUMIFS(Backlog!$H$3:$H$92,Backlog!$G$3:$G$92,$A4,Backlog!$F$3:$F$92,"Active") -> 6 | F4: =SUMIFS(Backlog!$H$3:$H$92,Backlog!$G$3:$G$92,$A4,Backlog!$F$3:$F$92,"Resolved") -> 13 | G4: =SUMIFS(Backlog!$H$3:$H$92,Backlog!$G$3:$G$92,$A4,Backlog!$F$3:$F$92,"Closed") -> 57 | H4: =SUMIFS(Backlog!$H$3:$H$92,Backlog!$G$3:$G$92,$A4,Backlog!$F$3:$F$92,"Blocked") -> 18 | I4: =F4+G4 -> 70 | J4: =IF(C4=0,0,I4/C4) -> 0.7 | K4: =COUNTIFS(Backlog!$G$3:$G$92,$A4,Backlog!$F$3:$F$92,"Blocked") -> 6 | L4: =SUMIFS(Backlog!$I$3:$I$92,Backlog!$G$3:$G$92,$A4) -> 38
A5: ZAV-HZN\Sprint 5 | B5: =COUNTIFS(Backlog!$G$3:$G$92,$A5) -> 20 | C5: =SUMIFS(Backlog!$H$3:$H$92,Backlog!$G$3:$G$92,$A5) -> 89 | D5: =SUMIFS(Backlog!$H$3:$H$92,Backlog!$G$3:$G$92,$A5,Backlog!$F$3:$F$92,"New") -> 89 | E5: =SUMIFS(Backlog!$H$3:$H$92,Backlog!$G$3:$G$92,$A5,Backlog!$F$3:$F$92,"Active") -> 0 | F5: =SUMIFS(Backlog!$H$3:$H$92,Backlog!$G$3:$G$92,$A5,Backlog!$F$3:$F$92,"Resolved") -> 0 | G5: =SUMIFS(Backlog!$H$3:$H$92,Backlog!$G$3:$G$92,$A5,Backlog!$F$3:$F$92,"Closed") -> 0 | H5: =SUMIFS(Backlog!$H$3:$H$92,Backlog!$G$3:$G$92,$A5,Backlog!$F$3:$F$92,"Blocked") -> 0 | I5: =F5+G5 -> 0 | J5: =IF(C5=0,0,I5/C5) -> 0 | K5: =COUNTIFS(Backlog!$G$3:$G$92,$A5,Backlog!$F$3:$F$92,"Blocked") -> 0 | L5: =SUMIFS(Backlog!$I$3:$I$92,Backlog!$G$3:$G$92,$A5) -> 16
A6: Total (Sprints 3–5) | B6: =SUM(B3:B5) -> 70 | C6: =SUM(C3:C5) -> 259 | D6: =SUM(D3:D5) -> 95 | E6: =SUM(E3:E5) -> 6 | F6: =SUM(F3:F5) -> 18 | G6: =SUM(G3:G5) -> 122 | H6: =SUM(H3:H5) -> 18 | I6: =SUM(I3:I5) -> 140 | J6: =IF(C6=0,0,I6/C6) -> 0.54054054 | K6: =SUM(K3:K5) -> 6 | L6: =SUM(L3:L5) -> 54
A8: Sprint 4 blocked items tagged CargoWise | B8: =COUNTIFS(Backlog!$F$3:$F$92,"Blocked",Backlog!$J$3:$J$92,"*CargoWise*") -> 6
A9: Sprint 4 end date | B9: 46318
A10: Check: items on Backlog (all sprints + release) | B10: =COUNTA(Backlog!$A$3:$A$92) -> 90
