Workbook

Sheet Read me
A1: Frontier Project Actuals – Zava Industrial Distribution
A2: Fictitious test data – Copilot for Frontier Consultancy scenario testing
A4: Item | B4: Detail
A5: Purpose | B5: Closed-project actuals from a comparable Frontier Consulting implementation, used as historical evidence when estimating new D365 bids (e.g. Zava, ZAV-RFP-2026-014). Copilot uses it to sanity-check estimates and apply lessons learned.
A6: Test-data notice | B6: Fictitious test data – Copilot for Frontier Consultancy scenario testing. All companies, people and figures are fictitious.
A7: Customer | B7: Zava Industrial Distribution LLC – distributor of industrial equipment, pumps, valves and electrical supplies; HQ Dubai, branches in Abu Dhabi and Dammam (fictitious).
A8: Scope | B8: D365 Sales, D365 Customer Service, D365 Finance; Power BI; 6 integrations; 8 data migration objects.
A9: Timeline | B9: Kick-off 6 Jan 2025 · Go-live 1 Dec 2025 · Hypercare to 31 Jan 2026 · Project closed 27 Feb 2026.
A10: Frontier team | B10: Practice Lead: Lorette Roos · Lead Solution Architect: Omar Khalil · Finance lead: James Okafor · PM: Priya Nair · CE Functional Lead: Lina Mansour · Technical Lead: Arjun Mehta · Data Migration Lead: Noura Al Hashimi
A11: Headline variances | B11: Data migration +38% · Integrations +27% · Reports +22% · Configuration, forms and workflows within ±10%.
A12: Units | B12: All effort in person-days. Variance % = (Actual − Estimated) ÷ Estimated.
A13: Sheet map
A14: Actuals | B14: 45 work packages with item type, complexity, estimated and actual days, variance and comment; totals by formula.
A15: Variance by Item Type | B15: Roll-up by item type (SUMIF formulas) with lessons learned.
A17: Fictitious test data – Copilot for Frontier Consultancy scenario testing

Sheet Actuals
A1: Zava Industrial Distribution – D365 implementation: estimate vs actual (closed project)
A2: D365 Sales + Customer Service + Finance · Project closed 27 Feb 2026 · Fictitious test data – Copilot for Frontier Consultancy scenario testing
A3: Work package | B3: Item type | C3: Complexity | D3: Estimated days | E3: Actual days | F3: Variance % | G3: Comment
A4: Sales – Account, contact & hierarchy model | B4: Configuration | C4: Medium | D4: 6 | E4: 6.5 | F4: =IF(D4=0,0,(E4-D4)/D4) -> 0.083333333 | G4: Minor rework after hierarchy workshop
A5: Sales – Lead-to-opportunity business process flow | B5: Workflow/Power Automate | C5: Medium | D5: 5 | E5: 5.5 | F5: =IF(D5=0,0,(E5-D5)/D5) -> 0.1 | G5: Extra stage (Site Visit) added in design
A6: Sales – Product catalogue & price lists | B6: Configuration | C6: Medium | D6: 8 | E6: 8.5 | F6: =IF(D6=0,0,(E6-D6)/D6) -> 0.0625 | G6: Three currencies; contract prices added
A7: Sales – Quote document template (Word) | B7: Configuration | C7: Simple | D7: 3 | E7: 3.5 | F7: =IF(D7=0,0,(E7-D7)/D7) -> 0.16666667 | G7: English only; Arabic layout descoped
A8: Sales – Quote discount approval flow | B8: Workflow/Power Automate | C8: Medium | D8: 5 | E8: 4.5 | F8: =IF(D8=0,0,(E8-D8)/D8) -> -0.1 | G8: Reused standard approval pattern
A9: Sales – Credit-hold check plug-in | B9: Plug-in | C9: Medium | D9: 8 | E9: 9.5 | F9: =IF(D9=0,0,(E9-D9)/D9) -> 0.1875 | G9: Finance API response slower than expected; caching added
A10: Sales – Opportunity & quote forms and views | B10: Form/view | C10: Medium | D10: 6 | E10: 6 | F10: =IF(D10=0,0,(E10-D10)/D10) -> 0 | G10: As estimated
A11: Sales – Security roles & business units | B11: Configuration | C11: Medium | D11: 4 | E11: 4.5 | F11: =IF(D11=0,0,(E11-D11)/D11) -> 0.125 | G11: Extra role for branch managers
A12: Customer Service – Case model & categories | B12: Configuration | C12: Medium | D12: 5 | E12: 5 | F12: =IF(D12=0,0,(E12-D12)/D12) -> 0 | G12: As estimated
A13: Customer Service – Unified routing & queues | B13: Configuration | C13: Complex | D13: 10 | E13: 11.5 | F13: =IF(D13=0,0,(E13-D13)/D13) -> 0.15 | G13: Skills-based routing tuned during UAT
A14: Customer Service – SLA & business-hours calendars | B14: Configuration | C14: Complex | D14: 8 | E14: 9 | F14: =IF(D14=0,0,(E14-D14)/D14) -> 0.125 | G14: Public-holiday calendars for 3 countries
A15: Customer Service – Email-to-case & templates | B15: Configuration | C15: Simple | D15: 4 | E15: 4 | F15: =IF(D15=0,0,(E15-D15)/D15) -> 0 | G15: As estimated
... A48: Data migration – Historical cases (24 months) | B48: Data migration object | C48: Simple | D48: 7 | E48: 9 | F48: =IF(D48=0,0,(E48-D48)/D48) -> 0.28571429 | G48: Attachment volumes larger than profiled
A49: Total | D49: =SUM(D4:D48) -> 364 | E49: =SUM(E4:E48) -> 432.5 | F49: =IF(D49=0,0,(E49-D49)/D49) -> 0.18818681 | G49: =COUNT(D4:D48)&" work packages" -> 45 work packages

Sheet Variance by Item Type
A1: Variance by item type – where estimates ran over
A2: Calculated from the Actuals sheet · Fictitious test data – Copilot for Frontier Consultancy scenario testing
A3: Item type | B3: Work packages | C3: Estimated days | D3: Actual days | E3: Variance (days) | F3: Variance %
A4: Configuration | B4: =COUNTIF(Actuals!$B$4:$B$48,A4) -> 16 | C4: =SUMIF(Actuals!$B$4:$B$48,A4,Actuals!$D$4:$D$48) -> 104 | D4: =SUMIF(Actuals!$B$4:$B$48,A4,Actuals!$E$4:$E$48) -> 111 | E4: =D4-C4 -> 7 | F4: =IF(C4=0,0,E4/C4) -> 0.067307692
A5: Form/view | B5: =COUNTIF(Actuals!$B$4:$B$48,A5) -> 2 | C5: =SUMIF(Actuals!$B$4:$B$48,A5,Actuals!$D$4:$D$48) -> 12 | D5: =SUMIF(Actuals!$B$4:$B$48,A5,Actuals!$E$4:$E$48) -> 12.5 | E5: =D5-C5 -> 0.5 | F5: =IF(C5=0,0,E5/C5) -> 0.041666667
A6: Workflow/Power Automate | B6: =COUNTIF(Actuals!$B$4:$B$48,A6) -> 3 | C6: =SUMIF(Actuals!$B$4:$B$48,A6,Actuals!$D$4:$D$48) -> 15 | D6: =SUMIF(Actuals!$B$4:$B$48,A6,Actuals!$E$4:$E$48) -> 15 | E6: =D6-C6 -> 0 | F6: =IF(C6=0,0,E6/C6) -> 0
A7: Plug-in | B7: =COUNTIF(Actuals!$B$4:$B$48,A7) -> 2 | C7: =SUMIF(Actuals!$B$4:$B$48,A7,Actuals!$D$4:$D$48) -> 17 | D7: =SUMIF(Actuals!$B$4:$B$48,A7,Actuals!$E$4:$E$48) -> 19.5 | E7: =D7-C7 -> 2.5 | F7: =IF(C7=0,0,E7/C7) -> 0.14705882
A8: X++ class | B8: =COUNTIF(Actuals!$B$4:$B$48,A8) -> 1 | C8: =SUMIF(Actuals!$B$4:$B$48,A8,Actuals!$D$4:$D$48) -> 10 | D8: =SUMIF(Actuals!$B$4:$B$48,A8,Actuals!$E$4:$E$48) -> 11 | E8: =D8-C8 -> 1 | F8: =IF(C8=0,0,E8/C8) -> 0.1
A9: Extension | B9: =COUNTIF(Actuals!$B$4:$B$48,A9) -> 1 | C9: =SUMIF(Actuals!$B$4:$B$48,A9,Actuals!$D$4:$D$48) -> 6 | D9: =SUMIF(Actuals!$B$4:$B$48,A9,Actuals!$E$4:$E$48) -> 6.5 | E9: =D9-C9 -> 0.5 | F9: =IF(C9=0,0,E9/C9) -> 0.083333333
A10: Report | B10: =COUNTIF(Actuals!$B$4:$B$48,A10) -> 6 | C10: =SUMIF(Actuals!$B$4:$B$48,A10,Actuals!$D$4:$D$48) -> 50 | D10: =SUMIF(Actuals!$B$4:$B$48,A10,Actuals!$E$4:$E$48) -> 61 | E10: =D10-C10 -> 11 | F10: =IF(C10=0,0,E10/C10) -> 0.22
A11: Integration | B11: =COUNTIF(Actuals!$B$4:$B$48,A11) -> 6 | C11: =SUMIF(Actuals!$B$4:$B$48,A11,Actuals!$D$4:$D$48) -> 100 | D11: =SUMIF(Actuals!$B$4:$B$48,A11,Actuals!$E$4:$E$48) -> 127 | E11: =D11-C11 -> 27 | F11: =IF(C11=0,0,E11/C11) -> 0.27
A12: Data migration object | B12: =COUNTIF(Actuals!$B$4:$B$48,A12) -> 8 | C12: =SUMIF(Actuals!$B$4:$B$48,A12,Actuals!$D$4:$D$48) -> 50 | D12: =SUMIF(Actuals!$B$4:$B$48,A12,Actuals!$E$4:$E$48) -> 69 | E12: =D12-C12 -> 19 | F12: =IF(C12=0,0,E12/C12) -> 0.38
A13: Total | B13: =SUM(B4:B12) -> 45 | C13: =SUM(C4:C12) -> 364 | D13: =SUM(D4:D12) -> 432.5 | E13: =SUM(E4:E12) -> 68.5 | F13: =IF(C13=0,0,E13/C13) -> 0.18818681
A14: Check: matches Actuals total (should be 0) | C14: =C13-Actuals!D49 -> 0 | D14: =D13-Actuals!E49 -> 0
A16: Lessons learned
A17: Data migration ran 38% over: legacy master data (customers, vendors) had high duplicate rates; budget at least 3 mock loads and a cleansing owner on the customer side.
A18: Integrations ran 27% over: third-party dependencies (bank certification, courier API limits, undocumented legacy WMS) – secure API specifications before fixing price.
A19: Reports ran 22% over: KPI definitions and the chart of accounts changed late; freeze report definitions at design sign-off and treat bilingual (Arabic) layouts as Complex.
A20: Configuration, forms and workflows landed within ±10% of estimate – the complexity matrix is reliable for these item types.
